bdayr/__init__.py
bdayr/__main__.py
bdayr-1.0.2.dist-info/METADATA
bdayr-1.0.2.dist-info/WHEEL
bdayr-1.0.2.dist-info/licenses/LICENSE
bdayr-1.0.2.dist-info/RECORD
